{
	"Players": [
		{
			"Name": "Scottie Scheffler",
			"Nationality": "United States",
			"Holes": [
				{
					"HoleNumber": 1,
					"Score": 4,
					"Shots":[
						{
							"Club": "Driver",
							"Distance": 289,
							"EndPosition": {
								"X": 10,
								"Y": 289
							}
						},
						{
							"Club": "5 Iron",
							"Distance": 189,
							"EndPosition": {
								"X": 30,
								"Y": 460
							}
						},
						{
							"Club": "52 Degree",
							"Distance": 26,
							"EndPosition":{
								"X": 30,
								"Y": 444
							}
						},
						{
							"Club": "Putter",
							"Distance" : 1,
							"EndPosition": {
								"X": 30,
								"Y": 445
							}
						}
					]
				},
				{
					"HoleNumber": 2,
					"Score": 5,
					"Shots": [
						{
							"Club": "Driver",
							"Distance": 338,
							"EndPosition": {
								"X": 30,
								"Y": 338
							}
						},
						{
							"Club": "6 Iron",
							"Distance": 197,
							"EndPosition": {
								"X": 30,
								"Y": 338
							}
						},
						{
							"Club": "56 Degree",
							"Distance": 44,
							"EndPosition": {
								"X": 30,
								"Y": 338
							}
						},
						{
							"Club": "Putter",
							"Distance": 4,
							"EndPosition": {
								"X": 30,
								"Y": 338
							}
						},
						{
							"Club": "Putter",
							"Distance": 1,
							"EndPosition": {
								"X": 30,
								"Y": 338
							}
						}
					]
				},
				{
					"HoleNumber": 3,
					"Score": 3
				},
				{
					"HoleNumber": 4,
					"Score": 3
				},
				{
					"HoleNumber": 5,
					"Score": 4
				},
				{
					"HoleNumber": 6,
					"Score": 3
				}
			]
		},
		{
			"Name": "Rory McIlroy",
			"Nationality": "Northern Ireland",
			"Holes": [
				{
					"HoleNumber": 1,
					"Score": 3,
					"Shots":[
						{
							"Club": "Driver",
							"Distance": 289,
							"EndPosition": {
								"X": 10,
								"Y": 289
							}
						},
						{
							"Club": "5 Iron",
							"Distance": 189,
							"EndPosition": {
								"X": 30,
								"Y": 460
							}
						},
						{
							"Club": "52 Degree",
							"Distance": 26,
							"EndPosition":{
								"X": 30,
								"Y": 444
							}
						},
						{
							"Club": "Putter",
							"Distance" : 1,
							"EndPosition": {
								"X": 30,
								"Y": 445
							}
						}
					]
				},
				{
					"HoleNumber": 2,
					"Score": 5
				},
				{
					"HoleNumber": 3,
					"Score": 3
				},
				{
					"HoleNumber": 4,
					"Score": 3
				},
				{
					"HoleNumber": 5,
					"Score": 4
				},
				{
					"HoleNumber": 6,
					"Score": 3
				}
			]
		}
	]
}